dk_validator/__init__.py
dk_validator/validator.py
dk_validator-0.1.0.dist-info/METADATA
dk_validator-0.1.0.dist-info/WHEEL
dk_validator-0.1.0.dist-info/RECORD
