Metadata-Version: 2.1
Name: dk-validator
Version: 0.1.0
Summary: A library for phone number validation using the NumLookUpAPI
Author: Darshak Kakani2
Author-email: darshak.kakani2@crestdatasys.com
Requires-Python: >=3.12,<4.0
Classifier: Programming Language :: Python :: 3
Classifier: Programming Language :: Python :: 3.12
